nonebot_plugin_anan_say-0.1.4.dist-info/METADATA
nonebot_plugin_anan_say-0.1.4.dist-info/WHEEL
nonebot_plugin_anan_say-0.1.4.dist-info/entry_points.txt
nonebot_plugin_anan_say-0.1.4.dist-info/licenses/LICENSE
nonebot_plugin_anan_say/SourceHanSansCN_Regular.otf
nonebot_plugin_anan_say/__init__.py
nonebot_plugin_anan_say/anan.png
nonebot_plugin_anan_say/anan_say.py
nonebot_plugin_anan_say/config.py
nonebot_plugin_anan_say/render.py
nonebot_plugin_anan_say/typing.py
nonebot_plugin_anan_say-0.1.4.dist-info/RECORD
