Metadata-Version: 2.1
Name: nonebot_plugin_anan_say
Version: 0.1.4
Summary: 一个向安安的素描本上渲染文字并发送出去的插件
Author-Email: "Mr.Lee" <chzxxuanzheng@gmail.com>
License: agpl
Requires-Python: >=3.10
Requires-Dist: nonebot-plugin-alconna>=0.60.2
Requires-Dist: nonebot2>=2.4.3
Requires-Dist: pillow>=11.3.0
